geedataextract/__init__.py
geedataextract/downloadData.py
geedataextract/pullGEEvarPackage.py
geedataextract-0.0.3.dist-info/LICENSE
geedataextract-0.0.3.dist-info/METADATA
geedataextract-0.0.3.dist-info/WHEEL
geedataextract-0.0.3.dist-info/top_level.txt
geedataextract-0.0.3.dist-info/RECORD
