Metadata-Version: 2.1
Name: geedataextract
Version: 0.0.3
Summary: Download environmental and remote sensing data from Google Earth Engine for uploaded point or polygon shapefiles
Home-page: https://github.com/ASchwantes/geedataextract
Author: Amanda Schwantes
Author-email: aschwantes@gmail.com
License: MIT
Platform: UNKNOWN
Classifier: Programming Language :: Python :: 3
Classifier: License :: OSI Approved :: MIT License
Classifier: Operating System :: OS Independent
Classifier: Development Status :: 3 - Alpha
Requires-Python: >=3.5
